{"v":"4.8.0","meta":{"g":"LottieFiles AE 3.1.1","a":"","k":"","d":"","tc":""},"fr":30,"ip":1,"op":49,"w":720,"h":720,"nm":"bone shib animation","ddd":0,"assets":[{"id":"comp_0","layers":[{"ddd":0,"ind":1,"ty":3,"nm":"Null 1","sr":1,"ks":{"o":{"a":0,"k":0,"ix":11},"r":{"a":0,"k":0,"ix":10},"p":{"a":1,"k":[{"i":{"x":0.848,"y":1},"o":{"x":0,"y":0},"t":9,"s":[359.133,329.711,0],"to":[0,0,0],"ti":[0,0,0]},{"i":{"x":1,"y":1},"o":{"x":0.138,"y":0},"t":29,"s":[359.133,297.711,0],"to":[0,0,0],"ti":[0,0,0]},{"t":48,"s":[359.133,329.711,0]}],"ix":2},"a":{"a":0,"k":[50,50,0],"ix":1},"s":{"a":0,"k":[100,100,100],"ix":6}},"ao":0,"ip":0,"op":300,"st":0,"bm":0},{"ddd":0,"ind":3,"ty":4,"nm":"Layer 3 Outlines","parent":1,"sr":1,"ks":{"o":{"a":0,"k":100,"ix":11},"r":{"a":0,"k":0,"ix":10},"p":{"a":0,"k":[-20.641,-19.766,0],"ix":2},"a":{"a":0,"k":[50.228,54.187,0],"ix":1},"s":{"a":0,"k":[100,100,100],"ix":6}},"ao":0,"shapes":[{"ty":"gr","it":[{"ind":0,"ty":"sh","ix":1,"ks":{"a":1,"k":[{"i":{"x":0.667,"y":1},"o":{"x":0.333,"y":0},"t":9,"s":[{"i":[[-0.226,0.206],[0.113,2.051],[-0.702,2.015],[-3.867,-10.109],[5.108,-6.386],[-1.299,-1.5],[-1.432,-6.727],[4.172,-1.649],[4.517,5.876],[3.452,3.54],[3.572,3.674],[3.633,-1.205],[3.55,6.7],[-5.598,4.572],[-2.834,0.941],[-2.413,1.058]],"o":[[1.679,-1.535],[-0.119,-2.131],[3.88,-11.151],[2.948,7.707],[-0.175,0.175],[4.315,4.981],[0.909,4.273],[-8.156,3.224],[-3.019,-3.927],[-3.618,-3.71],[-3.088,1.986],[-6.8,2.255],[-3.224,-6.086],[2.311,-1.887],[2.485,-0.822],[0.378,-0.165]],"v":[[-15.54,-18.063],[-16.102,-24.212],[-15.411,-30.536],[12.749,-29.406],[8.894,-6.795],[24.384,11.087],[36.819,28.347],[31.905,38.463],[13.344,29.206],[3.372,18.226],[-6.864,6.54],[-15.983,11.898],[-34.504,5.795],[-32.047,-12.266],[-24.207,-16.554],[-16.438,-17.503]],"c":true}]},{"i":{"x":0.667,"y":1},"o":{"x":0.333,"y":0},"t":29,"s":[{"i":[[-0.226,0.206],[-1.998,0.475],[-1.951,-0.863],[-2.491,-5.54],[5.108,-6.386],[-1.299,-1.5],[-1.432,-6.727],[4.172,-1.649],[4.517,5.876],[3.452,3.54],[3.572,3.674],[3.63,1.215],[3.762,5.385],[0.93,8.446],[-1.055,2.01],[-2.413,1.058]],"o":[[1.679,-1.535],[3.61,-0.859],[6.419,2.84],[3.384,7.526],[-0.175,0.175],[4.315,4.981],[0.909,4.273],[-8.156,3.224],[-3.019,-3.927],[-3.618,-3.71],[-3.628,0.265],[-4.759,-1.593],[-3.944,-5.646],[-0.327,-2.966],[1.715,-3.267],[0.378,-0.165]],"v":[[-15.165,-25.313],[-9.352,-27.212],[-2.286,-27.161],[5.999,-19.656],[4.644,-3.045],[21.384,14.087],[34.569,29.597],[31.905,38.463],[14.594,28.207],[5.622,16.226],[-4.114,3.79],[-11.483,3.023],[-18.879,-3.206],[-22.297,-11.391],[-20.707,-18.679],[-17.688,-22.879]],"c":true}]},{"t":47,"s":[{"i":[[-0.226,0.206],[0.113,2.051],[-0.702,2.015],[-3.867,-10.109],[5.108,-6.386],[-1.299,-1.5],[-1.432,-6.727],[4.172,-1.649],[4.517,5.876],[3.452,3.54],[3.572,3.674],[3.633,-1.205],[3.55,6.7],[-5.598,4.572],[-2.834,0.941],[-2.413,1.058]],"o":[[1.679,-1.535],[-0.119,-2.131],[3.88,-11.151],[2.948,7.707],[-0.175,0.175],[4.315,4.981],[0.909,4.273],[-8.156,3.224],[-3.019,-3.927],[-3.618,-3.71],[-3.088,1.986],[-6.8,2.255],[-3.224,-6.086],[2.311,-1.887],[2.485,-0.822],[0.378,-0.165]],"v":[[-15.54,-18.063],[-16.102,-24.212],[-15.411,-30.536],[12.749,-29.406],[8.894,-6.795],[24.384,11.087],[36.819,28.347],[31.905,38.463],[13.344,29.206],[3.372,18.226],[-6.864,6.54],[-15.983,11.898],[-34.504,5.795],[-32.047,-12.266],[-24.207,-16.554],[-16.438,-17.503]],"c":true}]}],"ix":2},"nm":"Path 1","mn":"ADBE Vector Shape - Group","hd":false},{"ty":"st","c":{"a":0,"k":[0,0,0,1],"ix":3},"o":{"a":0,"k":100,"ix":4},"w":{"a":0,"k":5,"ix":5},"lc":1,"lj":1,"ml":10,"bm":0,"nm":"Stroke 1","mn":"ADBE Vector Graphic - Stroke","hd":false},{"ty":"fl","c":{"a":0,"k":[1,1,1,1],"ix":4},"o":{"a":0,"k":100,"ix":5},"r":1,"bm":0,"nm":"Fill 1","mn":"ADBE Vector Graphic - Fill","hd":false},{"ty":"tr","p":{"a":0,"k":[50.228,54.187],"ix":2},"a":{"a":0,"k":[0,0],"ix":1},"s":{"a":0,"k":[100,100],"ix":3},"r":{"a":0,"k":0,"ix":6},"o":{"a":0,"k":100,"ix":7},"sk":{"a":0,"k":0,"ix":4},"sa":{"a":0,"k":0,"ix":5},"nm":"Transform"}],"nm":"Group 1","np":3,"cix":2,"bm":0,"ix":1,"mn":"ADBE Vector Group","hd":false}],"ip":0,"op":300,"st":0,"bm":0},{"ddd":0,"ind":4,"ty":4,"nm":"Layer 4 Outlines","parent":1,"sr":1,"ks":{"o":{"a":0,"k":100,"ix":11},"r":{"a":0,"k":0,"ix":10},"p":{"a":0,"k":[13.729,19.544,0],"ix":2},"a":{"a":0,"k":[77.698,74.632,0],"ix":1},"s":{"a":0,"k":[100,100,100],"ix":6}},"ao":0,"shapes":[{"ty":"gr","it":[{"ind":0,"ty":"sh","ix":1,"ks":{"a":1,"k":[{"i":{"x":0.833,"y":0.833},"o":{"x":0.167,"y":0.167},"t":9,"s":[{"i":[[-15.543,-17.163],[27.424,-24.836],[15.543,17.163],[-27.423,24.836]],"o":[[15.543,17.163],[-27.424,24.836],[-15.543,-17.163],[27.424,-24.836]],"v":[[49.655,-44.97],[28.143,31.076],[-49.655,44.97],[-28.144,-31.076]],"c":true}]},{"i":{"x":0.833,"y":0.833},"o":{"x":0.167,"y":0.167},"t":29,"s":[{"i":[[-15.543,-17.163],[27.424,-24.836],[15.543,17.163],[-27.423,24.836]],"o":[[15.543,17.163],[-27.424,24.836],[-15.543,-17.163],[27.424,-24.836]],"v":[[44.155,-39.47],[28.893,31.076],[-49.655,44.97],[-28.144,-31.076]],"c":true}]},{"t":48,"s":[{"i":[[-15.543,-17.163],[27.424,-24.836],[15.543,17.163],[-27.423,24.836]],"o":[[15.543,17.163],[-27.424,24.836],[-15.543,-17.163],[27.424,-24.836]],"v":[[49.655,-44.97],[28.143,31.076],[-49.655,44.97],[-28.144,-31.076]],"c":true}]}],"ix":2},"nm":"Path 1","mn":"ADBE Vector Shape - Group","hd":false},{"ty":"st","c":{"a":0,"k":[0,0,0,1],"ix":3},"o":{"a":0,"k":100,"ix":4},"w":{"a":0,"k":5,"ix":5},"lc":1,"lj":1,"ml":10,"bm":0,"nm":"Stroke 1","mn":"ADBE Vector Graphic - Stroke","hd":false},{"ty":"tr","p":{"a":0,"k":[77.698,74.633],"ix":2},"a":{"a":0,"k":[0,0],"ix":1},"s":{"a":0,"k":[100,100],"ix":3},"r":{"a":0,"k":0,"ix":6},"o":{"a":0,"k":100,"ix":7},"sk":{"a":0,"k":0,"ix":4},"sa":{"a":0,"k":0,"ix":5},"nm":"Transform"}],"nm":"Group 1","np":2,"cix":2,"bm":0,"ix":1,"mn":"ADBE Vector Group","hd":false}],"ip":0,"op":300,"st":0,"bm":0},{"ddd":0,"ind":5,"ty":4,"nm":"Layer 6 Outlines","parent":1,"sr":1,"ks":{"o":{"a":0,"k":100,"ix":11},"r":{"a":0,"k":0,"ix":10},"p":{"a":0,"k":[11.846,45.535,0],"ix":2},"a":{"a":0,"k":[54.271,29.495,0],"ix":1},"s":{"a":0,"k":[100,100,100],"ix":6}},"ao":0,"shapes":[{"ty":"gr","it":[{"ind":0,"ty":"sh","ix":1,"ks":{"a":1,"k":[{"i":{"x":0.833,"y":0.833},"o":{"x":0.167,"y":0.167},"t":9,"s":[{"i":[[-0.027,13.033],[-10.514,-2.095],[-10.159,3.274],[-7.671,6.955],[-5.078,10.238],[50.515,-12.849],[7.286,3.062]],"o":[[6.325,8.656],[10.743,2.141],[9.675,-3.118],[8.27,-7.498],[0,0],[-7.66,1.949],[-12.155,-5.109]],"v":[[-53.994,-4.936],[-28.632,13.6],[3.054,9.26],[30.119,-4.173],[54.021,-29.245],[-11.464,27.297],[-34.546,25.873]],"c":true}]},{"i":{"x":0.833,"y":0.833},"o":{"x":0.167,"y":0.167},"t":29,"s":[{"i":[[-12.984,14.44],[-10.597,-8.595],[-10.159,3.274],[-10.096,2.301],[-5.078,10.238],[43.986,-8.542],[7.286,3.062]],"o":[[-3.484,21.19],[8.508,6.901],[9.675,-3.118],[6.902,-1.573],[0,0],[-7.759,1.507],[-12.155,-5.109]],"v":[[-43.244,-34.936],[-38.632,9.85],[-4.696,18.51],[10.619,14.577],[30.271,0.505],[-12.964,28.547],[-45.296,22.373]],"c":true}]},{"t":48,"s":[{"i":[[-0.027,13.033],[-10.514,-2.095],[-10.159,3.274],[-7.671,6.955],[-5.078,10.238],[50.515,-12.849],[7.286,3.062]],"o":[[6.325,8.656],[10.743,2.141],[9.675,-3.118],[8.27,-7.498],[0,0],[-7.66,1.949],[-12.155,-5.109]],"v":[[-53.994,-4.936],[-28.632,13.6],[3.054,9.26],[30.119,-4.173],[54.021,-29.245],[-11.464,27.297],[-34.546,25.873]],"c":true}]}],"ix":2},"nm":"Path 1","mn":"ADBE Vector Shape - Group","hd":false},{"ty":"fl","c":{"a":0,"k":[0.745098039216,0.290196078431,0.129411764706,1],"ix":4},"o":{"a":0,"k":100,"ix":5},"r":1,"bm":0,"nm":"Fill 1","mn":"ADBE Vector Graphic - Fill","hd":false},{"ty":"tr","p":{"a":0,"k":[54.271,29.495],"ix":2},"a":{"a":0,"k":[0,0],"ix":1},"s":{"a":0,"k":[100,100],"ix":3},"r":{"a":0,"k":0,"ix":6},"o":{"a":0,"k":100,"ix":7},"sk":{"a":0,"k":0,"ix":4},"sa":{"a":0,"k":0,"ix":5},"nm":"Transform"}],"nm":"Group 1","np":2,"cix":2,"bm":0,"ix":1,"mn":"ADBE Vector Group","hd":false}],"ip":0,"op":300,"st":0,"bm":0},{"ddd":0,"ind":6,"ty":4,"nm":"Layer 8 Outlines","parent":1,"sr":1,"ks":{"o":{"a":0,"k":100,"ix":11},"r":{"a":0,"k":0,"ix":10},"p":{"a":0,"k":[128.633,132.211,0],"ix":2},"a":{"a":0,"k":[42.914,46.631,0],"ix":1},"s":{"a":0,"k":[100,100,100],"ix":6}},"ao":0,"shapes":[{"ty":"gr","it":[{"ind":0,"ty":"sh","ix":1,"ks":{"a":1,"k":[{"i":{"x":0.667,"y":1},"o":{"x":0.333,"y":0},"t":9,"s":[{"i":[[0,0],[-0.001,-0.001],[-0.226,0.044],[-5.937,-3.829],[1.324,-6.396],[8.467,1.05],[0.019,-0.316],[1.474,-3.339],[3.898,-1.252],[4.877,4.634],[0.163,4.437],[-0.553,2.163],[-0.328,1.199],[0.165,0.313],[2.558,4.412]],"o":[[0,0],[0.147,0.149],[6.483,-1.267],[5.973,3.853],[-2.023,9.767],[0.282,0.035],[-0.214,3.624],[-1.619,3.67],[-6.404,2.059],[-3.256,-3.095],[-0.083,-2.254],[0.305,-1.194],[0.145,-0.53],[-2.367,-4.517],[0,0]],"v":[[-11.652,-34.131],[-0.085,-22.419],[2.381,-22.965],[23.288,-21.428],[29.09,-1.98],[8.856,8.17],[8.877,13.421],[6.558,24.074],[-1.712,32.072],[-20.777,27.678],[-25.877,15.632],[-24.98,9.169],[-24.148,5.548],[-22.752,1.748],[-30.415,-11.531]],"c":true}]},{"i":{"x":0.667,"y":1},"o":{"x":0.333,"y":0},"t":29,"s":[{"i":[[0,0],[-0.001,-0.001],[-0.23,0.019],[-5.079,-4.713],[0.262,-6.522],[4.702,-8.94],[0.22,-0.222],[2.32,-1.291],[4.538,0.656],[5.543,3.503],[2.311,3.08],[-0.115,2.227],[-0.328,1.199],[0.165,0.313],[2.558,4.412]],"o":[[0,0],[0.147,0.149],[7.192,-0.581],[5.366,4.979],[-0.32,7.432],[0.282,0.035],[-3.827,3.774],[-3.489,1.888],[-6.625,-0.941],[-3.875,-2.449],[-1.297,-1.717],[0.16,-3.589],[0.145,-0.53],[-2.367,-4.517],[0,0]],"v":[[-14.265,-30.331],[-0.204,-15.294],[5.543,-13.965],[20.438,-8.959],[25.784,3.538],[22.593,15.11],[18.345,19.387],[12.408,23.292],[3.539,24.272],[-6.765,21.028],[-10.486,16.761],[-14.159,10.7],[-14.61,4.941],[-13.727,-2.29],[-27.09,-15.568]],"c":true}]},{"t":48,"s":[{"i":[[0,0],[-0.001,-0.001],[-0.226,0.044],[-5.937,-3.829],[1.324,-6.396],[8.467,1.05],[0.019,-0.316],[1.474,-3.339],[3.898,-1.252],[4.877,4.634],[0.163,4.437],[-0.553,2.163],[-0.328,1.199],[0.165,0.313],[2.558,4.412]],"o":[[0,0],[0.147,0.149],[6.483,-1.267],[5.973,3.853],[-2.023,9.767],[0.282,0.035],[-0.214,3.624],[-1.619,3.67],[-6.404,2.059],[-3.256,-3.095],[-0.083,-2.254],[0.305,-1.194],[0.145,-0.53],[-2.367,-4.517],[0,0]],"v":[[-11.652,-34.131],[-0.085,-22.419],[2.381,-22.965],[23.288,-21.428],[29.09,-1.98],[8.856,8.17],[8.877,13.421],[6.558,24.074],[-1.712,32.072],[-20.777,27.678],[-25.877,15.632],[-24.98,9.169],[-24.148,5.548],[-22.752,1.748],[-30.415,-11.531]],"c":true}]}],"ix":2},"nm":"Path 1","mn":"ADBE Vector Shape - Group","hd":false},{"ty":"st","c":{"a":0,"k":[0,0,0,1],"ix":3},"o":{"a":0,"k":100,"ix":4},"w":{"a":0,"k":5,"ix":5},"lc":1,"lj":2,"bm":0,"nm":"Stroke 1","mn":"ADBE Vector Graphic - Stroke","hd":false},{"ty":"fl","c":{"a":0,"k":[1,1,1,1],"ix":4},"o":{"a":0,"k":100,"ix":5},"r":1,"bm":0,"nm":"Fill 1","mn":"ADBE Vector Graphic - Fill","hd":false},{"ty":"tr","p":{"a":0,"k":[42.914,46.631],"ix":2},"a":{"a":0,"k":[0,0],"ix":1},"s":{"a":0,"k":[100,100],"ix":3},"r":{"a":0,"k":0,"ix":6},"o":{"a":0,"k":100,"ix":7},"sk":{"a":0,"k":0,"ix":4},"sa":{"a":0,"k":0,"ix":5},"nm":"Transform"}],"nm":"Group 1","np":3,"cix":2,"bm":0,"ix":1,"mn":"ADBE Vector Group","hd":false}],"ip":0,"op":300,"st":0,"bm":0},{"ddd":0,"ind":7,"ty":4,"nm":"Layer 9 Outlines","parent":1,"sr":1,"ks":{"o":{"a":0,"k":100,"ix":11},"r":{"a":0,"k":0,"ix":10},"p":{"a":0,"k":[56.114,57.229,0],"ix":2},"a":{"a":0,"k":[100.162,93.237,0],"ix":1},"s":{"a":0,"k":[100,100,100],"ix":6}},"ao":0,"shapes":[{"ty":"gr","it":[{"ind":0,"ty":"sh","ix":1,"ks":{"a":1,"k":[{"i":{"x":0.667,"y":1},"o":{"x":0.333,"y":0},"t":9,"s":[{"i":[[17.588,37.994],[0,0],[-18.09,-18.001],[13.305,-17.55],[19.06,-2.443],[4.52,1.187],[6.718,7.392],[7.163,7.626],[7.425,4.235],[5.37,4.261],[-48.238,54.519]],"o":[[0,0],[17.888,18.202],[19.791,19.694],[-11.154,14.714],[-4.6,0.59],[-9.951,-2.615],[-7.031,-7.737],[-5.984,-6.371],[-5.947,-3.393],[0,0],[0,0]],"v":[[8.845,-80.737],[14.198,-76.335],[67.871,-21.72],[55.139,48.916],[9.55,80.147],[-4.533,79.55],[-29.522,61.29],[-47.517,35.852],[-70.499,22.582],[-87.662,11.16],[-5.805,-15.154]],"c":true}]},{"i":{"x":0.667,"y":1},"o":{"x":0.333,"y":0},"t":29,"s":[{"i":[[17.588,37.994],[0,0],[-18.09,-18.001],[13.305,-17.55],[19.06,-2.443],[4.52,1.187],[6.718,7.392],[7.163,7.626],[7.425,4.235],[5.37,4.261],[-48.238,54.519]],"o":[[0,0],[18.556,31.395],[19.791,19.694],[-11.154,14.714],[-4.6,0.59],[-9.951,-2.615],[-7.031,-7.737],[-5.984,-6.371],[-5.947,-3.393],[0,0],[0,0]],"v":[[5.845,-74.737],[17.698,-64.335],[67.871,-21.72],[55.139,48.916],[9.55,80.147],[-4.533,79.55],[-32.022,64.29],[-52.517,43.852],[-73.999,24.582],[-87.662,11.16],[-5.805,-15.154]],"c":true}]},{"t":48,"s":[{"i":[[17.588,37.994],[0,0],[-18.09,-18.001],[13.305,-17.55],[19.06,-2.443],[4.52,1.187],[6.718,7.392],[7.163,7.626],[7.425,4.235],[5.37,4.261],[-48.238,54.519]],"o":[[0,0],[17.888,18.202],[19.791,19.694],[-11.154,14.714],[-4.6,0.59],[-9.951,-2.615],[-7.031,-7.737],[-5.984,-6.371],[-5.947,-3.393],[0,0],[0,0]],"v":[[8.845,-80.737],[14.198,-76.335],[67.871,-21.72],[55.139,48.916],[9.55,80.147],[-4.533,79.55],[-29.522,61.29],[-47.517,35.852],[-70.499,22.582],[-87.662,11.16],[-5.805,-15.154]],"c":true}]}],"ix":2},"nm":"Path 1","mn":"ADBE Vector Shape - Group","hd":false},{"ty":"st","c":{"a":0,"k":[0,0,0,1],"ix":3},"o":{"a":0,"k":100,"ix":4},"w":{"a":0,"k":5,"ix":5},"lc":1,"lj":1,"ml":10,"bm":0,"nm":"Stroke 1","mn":"ADBE Vector Graphic - Stroke","hd":false},{"ty":"tr","p":{"a":0,"k":[100.162,93.237],"ix":2},"a":{"a":0,"k":[0,0],"ix":1},"s":{"a":0,"k":[100,100],"ix":3},"r":{"a":0,"k":0,"ix":6},"o":{"a":0,"k":100,"ix":7},"sk":{"a":0,"k":0,"ix":4},"sa":{"a":0,"k":0,"ix":5},"nm":"Transform"}],"nm":"Group 1","np":2,"cix":2,"bm":0,"ix":1,"mn":"ADBE Vector Group","hd":false}],"ip":0,"op":300,"st":0,"bm":0},{"ddd":0,"ind":8,"ty":4,"nm":"Layer 10 Outlines","parent":1,"sr":1,"ks":{"o":{"a":0,"k":100,"ix":11},"r":{"a":0,"k":0,"ix":10},"p":{"a":0,"k":[32.367,104.602,0],"ix":2},"a":{"a":0,"k":[60.75,34.563,0],"ix":1},"s":{"a":0,"k":[100,100,100],"ix":6}},"ao":0,"shapes":[{"ty":"gr","it":[{"ind":0,"ty":"sh","ix":1,"ks":{"a":1,"k":[{"i":{"x":0.667,"y":1},"o":{"x":0.333,"y":0},"t":9,"s":[{"i":[[4.794,7.533],[-26,9],[0,0],[0,0],[-20.999,7],[0.956,-0.811],[4.705,-1.593],[8.652,2.987],[6.489,6.894],[4.327,5.897],[8.908,3.75]],"o":[[0,0],[0,0],[0,0],[0,0],[-1.132,0.378],[-3.793,3.221],[-8.596,2.909],[-9.219,-3.182],[-5.008,-5.321],[-5.803,-7.907],[-7.892,-3.324]],"v":[[-60.499,-34.313],[-21.499,-32.313],[-2.499,-13.313],[20.501,10.687],[60.499,19.687],[56.594,23.64],[43.63,30.877],[16.91,31.326],[-4.995,14.192],[-18.059,-3.976],[-39.588,-20.047]],"c":true}]},{"i":{"x":0.667,"y":1},"o":{"x":0.333,"y":0},"t":29,"s":[{"i":[[4.794,7.533],[-26,9],[-6.5,-10.5],[-4.5,-2],[-20.999,7],[0.956,-0.811],[4.705,-1.593],[8.652,2.987],[6.489,6.894],[4.327,5.897],[7.588,5.734]],"o":[[0,0],[0,0],[6.5,10.5],[4.5,2],[-1.132,0.378],[-3.793,3.221],[-8.596,2.909],[-9.219,-3.182],[-5.008,-5.321],[-5.803,-7.907],[-6.832,-5.163]],"v":[[-60.499,-34.313],[-21.499,-32.313],[-7.999,-7.813],[16.501,15.687],[60.499,19.687],[56.594,23.64],[43.63,30.877],[16.91,31.326],[-7.495,18.192],[-24.559,1.024],[-42.088,-15.047]],"c":true}]},{"t":48,"s":[{"i":[[4.794,7.533],[-26,9],[0,0],[0,0],[-20.999,7],[0.956,-0.811],[4.705,-1.593],[8.652,2.987],[6.489,6.894],[4.327,5.897],[8.908,3.75]],"o":[[0,0],[0,0],[0,0],[0,0],[-1.132,0.378],[-3.793,3.221],[-8.596,2.909],[-9.219,-3.182],[-5.008,-5.321],[-5.803,-7.907],[-7.892,-3.324]],"v":[[-60.499,-34.313],[-21.499,-32.313],[-2.499,-13.313],[20.501,10.687],[60.499,19.687],[56.594,23.64],[43.63,30.877],[16.91,31.326],[-4.995,14.192],[-18.059,-3.976],[-39.588,-20.047]],"c":true}]}],"ix":2},"nm":"Path 1","mn":"ADBE Vector Shape - Group","hd":false},{"ty":"fl","c":{"a":0,"k":[0.407843167174,0.098039223166,0.03137254902,1],"ix":4},"o":{"a":0,"k":100,"ix":5},"r":1,"bm":0,"nm":"Fill 1","mn":"ADBE Vector Graphic - Fill","hd":false},{"ty":"tr","p":{"a":0,"k":[60.749,34.563],"ix":2},"a":{"a":0,"k":[0,0],"ix":1},"s":{"a":0,"k":[100,100],"ix":3},"r":{"a":0,"k":0,"ix":6},"o":{"a":0,"k":100,"ix":7},"sk":{"a":0,"k":0,"ix":4},"sa":{"a":0,"k":0,"ix":5},"nm":"Transform"}],"nm":"Group 1","np":2,"cix":2,"bm":0,"ix":1,"mn":"ADBE Vector Group","hd":false}],"ip":0,"op":300,"st":0,"bm":0},{"ddd":0,"ind":9,"ty":4,"nm":"Layer 11 Outlines","parent":1,"sr":1,"ks":{"o":{"a":0,"k":100,"ix":11},"r":{"a":0,"k":0,"ix":10},"p":{"a":0,"k":[56.114,57.229,0],"ix":2},"a":{"a":0,"k":[87.912,80.987,0],"ix":1},"s":{"a":0,"k":[100,100,100],"ix":6}},"ao":0,"shapes":[{"ty":"gr","it":[{"ind":0,"ty":"sh","ix":1,"ks":{"a":1,"k":[{"i":{"x":0.667,"y":1},"o":{"x":0.333,"y":0},"t":9,"s":[{"i":[[17.588,37.994],[0,0],[-18.09,-18.001],[13.305,-17.55],[19.06,-2.443],[4.52,1.187],[6.718,7.392],[7.163,7.626],[7.425,4.235],[5.37,4.261],[-48.238,54.519]],"o":[[0,0],[17.888,18.202],[19.791,19.694],[-11.154,14.714],[-4.6,0.59],[-9.951,-2.615],[-7.031,-7.737],[-5.984,-6.371],[-5.947,-3.393],[0,0],[0,0]],"v":[[8.845,-80.737],[14.198,-76.335],[67.871,-21.72],[55.139,48.916],[9.55,80.147],[-4.533,79.55],[-29.522,61.29],[-47.517,35.852],[-70.499,22.582],[-87.662,11.16],[-5.805,-15.154]],"c":true}]},{"i":{"x":0.667,"y":1},"o":{"x":0.333,"y":0},"t":29,"s":[{"i":[[17.588,37.994],[0,0],[-31.617,-17.72],[13.305,-17.55],[19.06,-2.443],[4.52,1.187],[6.718,7.392],[7.163,7.626],[7.425,4.235],[5.37,4.261],[-48.238,54.519]],"o":[[0,0],[9.056,19.395],[24.356,13.65],[-11.154,14.714],[-4.6,0.59],[-9.951,-2.615],[-7.031,-7.737],[-5.984,-6.371],[-5.947,-3.393],[0,0],[0,0]],"v":[[4.095,-77.737],[14.948,-69.335],[67.871,-21.72],[55.139,48.916],[9.55,80.147],[-4.533,79.55],[-29.522,61.29],[-47.517,35.852],[-70.499,22.582],[-87.662,11.16],[-5.805,-15.154]],"c":true}]},{"t":48,"s":[{"i":[[17.588,37.994],[0,0],[-18.09,-18.001],[13.305,-17.55],[19.06,-2.443],[4.52,1.187],[6.718,7.392],[7.163,7.626],[7.425,4.235],[5.37,4.261],[-48.238,54.519]],"o":[[0,0],[17.888,18.202],[19.791,19.694],[-11.154,14.714],[-4.6,0.59],[-9.951,-2.615],[-7.031,-7.737],[-5.984,-6.371],[-5.947,-3.393],[0,0],[0,0]],"v":[[8.845,-80.737],[14.198,-76.335],[67.871,-21.72],[55.139,48.916],[9.55,80.147],[-4.533,79.55],[-29.522,61.29],[-47.517,35.852],[-70.499,22.582],[-87.662,11.16],[-5.805,-15.154]],"c":true}]}],"ix":2},"nm":"Path 1","mn":"ADBE Vector Shape - Group","hd":false},{"ty":"fl","c":{"a":0,"k":[0.737254901961,0.270588235294,0.101960791794,1],"ix":4},"o":{"a":0,"k":100,"ix":5},"r":1,"bm":0,"nm":"Fill 1","mn":"ADBE Vector Graphic - Fill","hd":false},{"ty":"tr","p":{"a":0,"k":[87.912,80.987],"ix":2},"a":{"a":0,"k":[0,0],"ix":1},"s":{"a":0,"k":[100,100],"ix":3},"r":{"a":0,"k":0,"ix":6},"o":{"a":0,"k":100,"ix":7},"sk":{"a":0,"k":0,"ix":4},"sa":{"a":0,"k":0,"ix":5},"nm":"Transform"}],"nm":"Group 1","np":2,"cix":2,"bm":0,"ix":1,"mn":"ADBE Vector Group","hd":false}],"ip":0,"op":300,"st":0,"bm":0},{"ddd":0,"ind":10,"ty":4,"nm":"Layer 12 Outlines","parent":1,"sr":1,"ks":{"o":{"a":0,"k":100,"ix":11},"r":{"a":0,"k":0,"ix":10},"p":{"a":0,"k":[13.729,19.544,0],"ix":2},"a":{"a":0,"k":[77.698,74.632,0],"ix":1},"s":{"a":0,"k":[100,100,100],"ix":6}},"ao":0,"shapes":[{"ty":"gr","it":[{"ind":0,"ty":"sh","ix":1,"ks":{"a":1,"k":[{"i":{"x":0.833,"y":0.833},"o":{"x":0.167,"y":0.167},"t":9,"s":[{"i":[[-15.543,-17.163],[27.424,-24.836],[15.543,17.163],[-27.423,24.836]],"o":[[15.543,17.163],[-27.424,24.836],[-15.543,-17.163],[27.424,-24.836]],"v":[[49.655,-44.97],[28.143,31.076],[-49.655,44.97],[-28.144,-31.076]],"c":true}]},{"i":{"x":0.833,"y":0.833},"o":{"x":0.167,"y":0.167},"t":29,"s":[{"i":[[-15.543,-17.163],[27.424,-24.836],[15.543,17.163],[-27.423,24.836]],"o":[[15.543,17.163],[-27.424,24.836],[-15.543,-17.163],[27.424,-24.836]],"v":[[45.655,-39.22],[31.143,33.326],[-49.655,44.97],[-28.144,-31.076]],"c":true}]},{"t":48,"s":[{"i":[[-15.543,-17.163],[27.424,-24.836],[15.543,17.163],[-27.423,24.836]],"o":[[15.543,17.163],[-27.424,24.836],[-15.543,-17.163],[27.424,-24.836]],"v":[[49.655,-44.97],[28.143,31.076],[-49.655,44.97],[-28.144,-31.076]],"c":true}]}],"ix":2},"nm":"Path 1","mn":"ADBE Vector Shape - Group","hd":false},{"ty":"st","c":{"a":0,"k":[0,0,0,1],"ix":3},"o":{"a":0,"k":100,"ix":4},"w":{"a":0,"k":5,"ix":5},"lc":1,"lj":1,"ml":10,"bm":0,"nm":"Stroke 1","mn":"ADBE Vector Graphic - Stroke","hd":false},{"ty":"tr","p":{"a":0,"k":[77.698,74.633],"ix":2},"a":{"a":0,"k":[0,0],"ix":1},"s":{"a":0,"k":[100,100],"ix":3},"r":{"a":0,"k":0,"ix":6},"o":{"a":0,"k":100,"ix":7},"sk":{"a":0,"k":0,"ix":4},"sa":{"a":0,"k":0,"ix":5},"nm":"Transform"}],"nm":"Group 1","np":2,"cix":2,"bm":0,"ix":1,"mn":"ADBE Vector Group","hd":false}],"ip":0,"op":300,"st":0,"bm":0},{"ddd":0,"ind":11,"ty":4,"nm":"Layer 13 Outlines","parent":1,"sr":1,"ks":{"o":{"a":0,"k":100,"ix":11},"r":{"a":0,"k":0,"ix":10},"p":{"a":0,"k":[13.729,19.544,0],"ix":2},"a":{"a":0,"k":[65.448,62.382,0],"ix":1},"s":{"a":0,"k":[100,100,100],"ix":6}},"ao":0,"shapes":[{"ty":"gr","it":[{"ind":0,"ty":"sh","ix":1,"ks":{"a":1,"k":[{"i":{"x":0.833,"y":0.833},"o":{"x":0.167,"y":0.167},"t":9,"s":[{"i":[[-15.543,-17.163],[27.424,-24.836],[15.543,17.163],[-27.423,24.836]],"o":[[15.543,17.163],[-27.424,24.836],[-15.543,-17.163],[27.424,-24.836]],"v":[[49.655,-44.97],[28.143,31.076],[-49.655,44.97],[-28.144,-31.076]],"c":true}]},{"i":{"x":0.833,"y":0.833},"o":{"x":0.167,"y":0.167},"t":29,"s":[{"i":[[-15.543,-17.163],[27.424,-24.836],[15.543,17.163],[-27.423,24.836]],"o":[[15.543,17.163],[-27.424,24.836],[-15.543,-17.163],[27.424,-24.836]],"v":[[44.405,-40.47],[29.893,33.076],[-49.655,44.97],[-28.144,-31.076]],"c":true}]},{"t":48,"s":[{"i":[[-15.543,-17.163],[27.424,-24.836],[15.543,17.163],[-27.423,24.836]],"o":[[15.543,17.163],[-27.424,24.836],[-15.543,-17.163],[27.424,-24.836]],"v":[[49.655,-44.97],[28.143,31.076],[-49.655,44.97],[-28.144,-31.076]],"c":true}]}],"ix":2},"nm":"Path 1","mn":"ADBE Vector Shape - Group","hd":false},{"ty":"fl","c":{"a":0,"k":[0.945098099054,0.490196108351,0.243137269862,1],"ix":4},"o":{"a":0,"k":100,"ix":5},"r":1,"bm":0,"nm":"Fill 1","mn":"ADBE Vector Graphic - Fill","hd":false},{"ty":"tr","p":{"a":0,"k":[65.448,62.383],"ix":2},"a":{"a":0,"k":[0,0],"ix":1},"s":{"a":0,"k":[100,100],"ix":3},"r":{"a":0,"k":0,"ix":6},"o":{"a":0,"k":100,"ix":7},"sk":{"a":0,"k":0,"ix":4},"sa":{"a":0,"k":0,"ix":5},"nm":"Transform"}],"nm":"Group 1","np":2,"cix":2,"bm":0,"ix":1,"mn":"ADBE Vector Group","hd":false}],"ip":0,"op":300,"st":0,"bm":0},{"ddd":0,"ind":12,"ty":4,"nm":"Layer 5 Outlines","sr":1,"ks":{"o":{"a":0,"k":58,"ix":11},"r":{"a":0,"k":0,"ix":10},"p":{"a":0,"k":[360,493,0],"ix":2},"a":{"a":0,"k":[72.25,7.93,0],"ix":1},"s":{"a":1,"k":[{"i":{"x":[0.848,0.848,0.848],"y":[1,1,1]},"o":{"x":[0.001,0.001,0.001],"y":[0,0,0]},"t":9,"s":[100,100,100]},{"i":{"x":[0.999,0.999,0.999],"y":[1,1,1]},"o":{"x":[0.138,0.138,0.138],"y":[0,0,0]},"t":29,"s":[81,100,100]},{"t":48,"s":[100,100,100]}],"ix":6}},"ao":0,"shapes":[{"ty":"gr","it":[{"ind":0,"ty":"sh","ix":1,"ks":{"a":0,"k":{"i":[[0,-4.242],[39.764,0],[0,4.242],[-39.764,0]],"o":[[0,4.242],[-39.764,0],[0,-4.242],[39.764,0]],"v":[[72,0],[0,7.68],[-72,0],[0,-7.68]],"c":true},"ix":2},"nm":"Path 1","mn":"ADBE Vector Shape - Group","hd":false},{"ty":"fl","c":{"a":0,"k":[0.560784313725,0,0,1],"ix":4},"o":{"a":0,"k":100,"ix":5},"r":1,"bm":0,"nm":"Fill 1","mn":"ADBE Vector Graphic - Fill","hd":false},{"ty":"tr","p":{"a":0,"k":[72.25,7.93],"ix":2},"a":{"a":0,"k":[0,0],"ix":1},"s":{"a":0,"k":[100,100],"ix":3},"r":{"a":0,"k":0,"ix":6},"o":{"a":0,"k":100,"ix":7},"sk":{"a":0,"k":0,"ix":4},"sa":{"a":0,"k":0,"ix":5},"nm":"Transform"}],"nm":"Group 1","np":2,"cix":2,"bm":0,"ix":1,"mn":"ADBE Vector Group","hd":false}],"ip":0,"op":300,"st":0,"bm":0}]}],"layers":[{"ddd":0,"ind":1,"ty":0,"nm":"Pre-comp 1","refId":"comp_0","sr":1,"ks":{"o":{"a":0,"k":100,"ix":11},"r":{"a":0,"k":0,"ix":10},"p":{"a":0,"k":[360,360,0],"ix":2},"a":{"a":0,"k":[360,360,0],"ix":1},"s":{"a":0,"k":[170,170,100],"ix":6}},"ao":0,"w":720,"h":720,"ip":0,"op":300,"st":0,"bm":0}],"markers":[]}